enterprise_extensions/__init__.py
enterprise_extensions/blocks.py
enterprise_extensions/checks.py
enterprise_extensions/deterministic.py
enterprise_extensions/dropout.py
enterprise_extensions/empirical_distr.py
enterprise_extensions/gp_kernels.py
enterprise_extensions/hypermodel.py
enterprise_extensions/load_feathers.py
enterprise_extensions/model_orfs.py
enterprise_extensions/model_utils.py
enterprise_extensions/models.py
enterprise_extensions/sampler.py
enterprise_extensions/sky_scrambles.py
enterprise_extensions/timing.py
enterprise_extensions/chromatic/ACE_SWEPAM_daily_proton_density_1998_2018_MJD_cm-3.txt
enterprise_extensions/chromatic/__init__.py
enterprise_extensions/chromatic/chromatic.py
enterprise_extensions/chromatic/solar_wind.py
enterprise_extensions/frequentist/F_statistic.py
enterprise_extensions/frequentist/Fe_statistic.py
enterprise_extensions/frequentist/__init__.py
enterprise_extensions/frequentist/chi_squared.py
enterprise_extensions/frequentist/optimal_statistic.py
enterprise_extensions-3.0.3.dist-info/licenses/AUTHORS.rst
enterprise_extensions-3.0.3.dist-info/licenses/LICENSE
enterprise_extensions-3.0.3.dist-info/METADATA
enterprise_extensions-3.0.3.dist-info/WHEEL
enterprise_extensions-3.0.3.dist-info/top_level.txt
enterprise_extensions-3.0.3.dist-info/RECORD
