Metadata-Version: 2.4
Name: enterprise_extensions
Version: 3.0.3
Summary: Extensions, model shortcuts, and utilities for the enterprise PTA analysis framework.
Home-page: https://github.com/stevertaylor/enterprise_extensions
Author: Stephen R. Taylor, Paul T. Baker, Jeffrey S. Hazboun, Sarah Vigeland
Author-email: jeffrey.hazboun@gmail.com
License: MIT
Keywords: gravitational-wave,black-hole binary,pulsar-timing arrays
Classifier: Topic :: Scientific/Engineering :: Astronomy
Classifier: Topic :: Scientific/Engineering :: Physics
Classifier: Topic :: Scientific/Engineering :: Mathematics
Classifier: Intended Audience :: Science/Research
Classifier: Programming Language :: Python :: 3
Classifier: Topic :: Software Development :: Libraries :: Python Modules
License-File: LICENSE
License-File: AUTHORS.rst
Requires-Dist: numpy>=1.16.3
Requires-Dist: scipy>=1.2.0
Requires-Dist: ephem>=3.7.6.0
Requires-Dist: healpy>=1.14.0
Requires-Dist: scikit-sparse>=0.4.5
Requires-Dist: enterprise-pulsar>=3.4.4
Requires-Dist: pyarrow>=16.1.0
Requires-Dist: scikit-learn>=0.24
Requires-Dist: matplotlib>=3.1.0
Requires-Dist: six
Requires-Dist: emcee
Requires-Dist: ptmcmcsampler
Dynamic: author
Dynamic: author-email
Dynamic: classifier
Dynamic: description
Dynamic: description-content-type
Dynamic: home-page
Dynamic: keywords
Dynamic: license
Dynamic: license-file
Dynamic: requires-dist
Dynamic: summary
